autotools/__init__.py
autotools/audio.py
autotools/chatgpt.py
autotools/chatgpt_presets.py
autotools/chats.py
autotools/img.py
autotools/module_get.py
autotools/temp_download.py
autotools/to_ipv4.py
autotools-0.7.dist-info/METADATA
autotools-0.7.dist-info/WHEEL
autotools-0.7.dist-info/top_level.txt
autotools-0.7.dist-info/RECORD
