Metadata-Version: 2.1
Name: autotools
Version: 0.7
Summary: Just save your time
Author: automatic, ebu sobak
Author-email: 
License: OpenSource
Requires-Dist: openai
Requires-Dist: SpeechRecognition
Requires-Dist: playsound
Requires-Dist: gtts
Requires-Dist: requests
Requires-Dist: Pillow
Requires-Dist: numpy
